locopt/__init__.py
locopt/client.py
locopt/helpers.py
locopt-1.0.0.dist-info/LICENCE
locopt-1.0.0.dist-info/METADATA
locopt-1.0.0.dist-info/WHEEL
locopt-1.0.0.dist-info/top_level.txt
locopt-1.0.0.dist-info/RECORD
