Metadata-Version: 2.1
Name: locopt
Version: 1.0.0
Summary: Localized template access and format.
Home-page: https://github.com/Exahilosys/locopt
Author: Exahilosys
License: MIT
Platform: UNKNOWN
Provides-Extra: docs
Requires-Dist: sphinx ; extra == 'docs'
